rongo/__init__.py
rongo/helper.py
rongo/cache/Cache.py
rongo/cache/TagSet.py
rongo/cache/__init__.py
rongo/cache/drivers/RedisDriver.py
rongo/cache/drivers/__init__.py
rongo/configuration/Configuration.py
rongo/configuration/__init__.py
rongo/configuration/helpers.py
rongo/configuration/providers/ConfigurationProvider.py
rongo/configuration/providers/__init__.py
rongo/container/Container.py
rongo/container/__init__.py
rongo/contract/CacheHandlerInterface.py
rongo/contract/__init__.py
rongo/environment/__init__.py
rongo/environment/environment.py
rongo/exceptions/Exceptions.py
rongo/exceptions/__init__.py
rongo/facades/Application.py
rongo/facades/Cache.py
rongo/facades/Config.py
rongo/facades/Facade.py
rongo/facades/Loader.py
rongo/facades/__init__.py
rongo/foundation/Application.py
rongo/foundation/Manager.py
rongo/foundation/__init__.py
rongo/loader/Loader.py
rongo/loader/__init__.py
rongo/providers/CacheProvider.py
rongo/providers/Provider.py
rongo/providers/__init__.py
rongo/utils/__init__.py
rongo/utils/collections.py
rongo/utils/console.py
rongo/utils/filesystem.py
rongo/utils/location.py
rongo/utils/singleton.py
rongo/utils/str.py
rongo/utils/structures.py
rongo-0.0.3.dist-info/LICENSE
rongo-0.0.3.dist-info/METADATA
rongo-0.0.3.dist-info/WHEEL
rongo-0.0.3.dist-info/top_level.txt
rongo-0.0.3.dist-info/RECORD
