Metadata-Version: 2.1
Name: rongo
Version: 0.0.3
Summary: This is not a python web framework, it's a complement to such mini frameworks like fastapi sanic. Mainly refer to Thinkphp Laravel Django Masonite.
Home-page: https://github.com/goophps/rongo.git
Author: randolph
Author-email: goophps@gmail.com
Classifier: Programming Language :: Python :: 3.7
Classifier: Programming Language :: Python :: 3.8
Classifier: Programming Language :: Python :: 3.9
Classifier: Programming Language :: Python :: 3.10
Classifier: License :: OSI Approved :: MIT License
Classifier: Operating System :: OS Independent
License-File: LICENSE
